Dempster_Shafer_utils.py
ecolaf.py
ecolaf-1.0.1.dist-info/LICENSE
ecolaf-1.0.1.dist-info/METADATA
ecolaf-1.0.1.dist-info/WHEEL
ecolaf-1.0.1.dist-info/top_level.txt
ecolaf-1.0.1.dist-info/RECORD
