Metadata-Version: 2.1
Name: ecolaf
Version: 1.0.1
Summary: A toolkit python package to build an adaptive multimodal late fusion pipeline based on Dempster-Shafer Theory for semantic segmentation and classification tasks.
Home-page: https://github.com/deregnaucourtlucas/ECOLAF
Author: Lucas Deregnaucourt
Author-email: lucas.deregnaucourt@insa-rouen.fr
Keywords: Dempster-Shafer Theory,Deep Learning,Multimodal,Semantic Segmentation,Classification
License-File: LICENSE
Requires-Dist: torch
